krpc/__init__.py
krpc/client.py
krpc/core.py
krpc/errors.py
krpc/message.py
krpc/models.py
kylin_rpc-0.0.2.dist-info/METADATA
kylin_rpc-0.0.2.dist-info/WHEEL
kylin_rpc-0.0.2.dist-info/RECORD
